tweepy/__init__.py
tweepy/api.py
tweepy/auth.py
tweepy/cache.py
tweepy/client.py
tweepy/cursor.py
tweepy/direct_message_event.py
tweepy/errors.py
tweepy/list.py
tweepy/media.py
tweepy/mixins.py
tweepy/models.py
tweepy/pagination.py
tweepy/parsers.py
tweepy/place.py
tweepy/poll.py
tweepy/space.py
tweepy/streaming.py
tweepy/tweet.py
tweepy/user.py
tweepy/utils.py
tweepy/asynchronous/__init__.py
tweepy/asynchronous/client.py
tweepy/asynchronous/pagination.py
tweepy/asynchronous/streaming.py
tweepy-4.13.0.dist-info/LICENSE
tweepy-4.13.0.dist-info/METADATA
tweepy-4.13.0.dist-info/WHEEL
tweepy-4.13.0.dist-info/top_level.txt
tweepy-4.13.0.dist-info/zip-safe
tweepy-4.13.0.dist-info/RECORD
