Metadata-Version: 2.1
Name: tweepy
Version: 4.13.0
Summary: Twitter library for Python
Home-page: https://www.tweepy.org/
Download-URL: https://pypi.org/project/tweepy/
Author: Joshua Roesslein
Author-email: tweepy@googlegroups.com
License: MIT
Project-URL: Documentation, https://tweepy.readthedocs.io
Project-URL: Issue Tracker, https://github.com/tweepy/tweepy/issues
Project-URL: Source Code, https://github.com/tweepy/tweepy
Keywords: twitter library
Classifier: Development Status :: 5 - Production/Stable
Classifier: Topic :: Software Development :: Libraries
Classifier: License :: OSI Approved :: MIT License
Classifier: Operating System :: OS Independent
Classifier: Programming Language :: Python
Classifier: Programming Language :: Python :: 3
Classifier: Programming Language :: Python :: 3.7
Classifier: Programming Language :: Python :: 3.8
Classifier: Programming Language :: Python :: 3.9
Classifier: Programming Language :: Python :: 3.10
Classifier: Programming Language :: Python :: 3.11
Classifier: Programming Language :: Python :: 3 :: Only
Requires-Python: >=3.7
Provides-Extra: async
Provides-Extra: docs
Provides-Extra: dev
Provides-Extra: socks
Provides-Extra: test
License-File: LICENSE
